mkml/__init__.py
mkml/mkml_base.py
mkml/mkml_meta.py
mkml/plugin/__init__.py
mkml/plugin/base.py
mkml/plugin/local_datasource.py
mkml/plugin/monitoring.py
mkml/plugin/standardization.py
mkml-0.0.2.dist-info/METADATA
mkml-0.0.2.dist-info/WHEEL
mkml-0.0.2.dist-info/top_level.txt
mkml-0.0.2.dist-info/RECORD
