Metadata-Version: 2.1
Name: mkml
Version: 0.0.2
Summary: Microkernel Architecture for Machine Learning
Home-page: https://github.com/ahhuisg/mkml
Author: ahhuisg
Author-email: yanhui79@gmail.com
License: UNKNOWN
Platform: UNKNOWN
Requires-Dist: logzero (==1.5.0)
Requires-Dist: numpy (==1.20.1)
Requires-Dist: scikit-learn (==0.24.1)
